README
setup.py
bin/vcfstoreclient
vcfstoreclient/__init__.py
vcfstoreclient/apiclient.py
vcfstoreclient.egg-info/PKG-INFO
vcfstoreclient.egg-info/SOURCES.txt
vcfstoreclient.egg-info/dependency_links.txt
vcfstoreclient.egg-info/not-zip-safe
vcfstoreclient.egg-info/requires.txt
vcfstoreclient.egg-info/top_level.txt