Metadata-Version: 1.0
Name: vcfstoreclient
Version: 0.4
Summary: Client for AWS vcfstore
Home-page: https://genomeinfo.github.io/
Author: Conrad Leonard
Author-email: conrad.leonard@qimrberghofer.edu.au
License: MIT
Platform: UNKNOWN
